LICENSE
README.md
pyproject.toml
asynkio/__init__.py
asynkio.egg-info/PKG-INFO
asynkio.egg-info/SOURCES.txt
asynkio.egg-info/dependency_links.txt
asynkio.egg-info/requires.txt
asynkio.egg-info/top_level.txt
asynkio/time/__init__.py
asynkio/time/interval.py
asynkio/time/types.py
tests/test_interval.py
tests/test_interval_burst.py
tests/test_interval_delay.py
tests/test_interval_skip.py
tests/test_time_types.py