Metadata-Version: 2.4
Name: asynkio
Version: 0.0.2
Summary: Tokio-like functionality for Python
Author-email: Matt Wilson <matthew@synesis.com.au>
Project-URL: Changelog, https://github.com/synesissoftware/asynkio/releases
Project-URL: Homepage, https://github.com/synesissoftware/asynkio
Project-URL: Issues, https://github.com/synesissoftware/asynkio/issues
Requires-Python: >=3.11
License-File: LICENSE
Requires-Dist: asyncio
Requires-Dist: diagnosticism
Requires-Dist: pytest>=8.4.1
Provides-Extra: dev
Requires-Dist: aiofiles; extra == "dev"
Requires-Dist: pyclasp>=0.8.10; extra == "dev"
Requires-Dist: pytest>=7.4.4; extra == "dev"
Provides-Extra: test
Requires-Dist: aiofiles; extra == "test"
Requires-Dist: pyclasp>=0.8.10; extra == "test"
Requires-Dist: pytest>=7.4.4; extra == "test"
Dynamic: license-file
